datalad_next/__init__.py
datalad_next/_version.py
datalad_next/conftest.py
datalad_next/annexbackends/__init__.py
datalad_next/annexbackends/base.py
datalad_next/annexbackends/xdlra.py
datalad_next/annexbackends/tests/__init__.py
datalad_next/annexbackends/tests/test_base.py
datalad_next/annexremotes/__init__.py
datalad_next/annexremotes/archivist.py
datalad_next/annexremotes/uncurl.py
datalad_next/annexremotes/tests/__init__.py
datalad_next/annexremotes/tests/test_archivist.py
datalad_next/annexremotes/tests/test_uncurl.py
datalad_next/archive_operations/__init__.py
datalad_next/archive_operations/base.py
datalad_next/archive_operations/tarfile.py
datalad_next/archive_operations/zipfile.py
datalad_next/archive_operations/tests/__init__.py
datalad_next/archive_operations/tests/test_tarfile.py
datalad_next/archive_operations/tests/test_zipfile.py
datalad_next/commands/__init__.py
datalad_next/commands/create_sibling_webdav.py
datalad_next/commands/credentials.py
datalad_next/commands/download.py
datalad_next/commands/ls_file_collection.py
datalad_next/commands/results.py
datalad_next/commands/status.py
datalad_next/commands/tree.py
datalad_next/commands/tests/__init__.py
datalad_next/commands/tests/test_create_sibling_webdav.py
datalad_next/commands/tests/test_credentials.py
datalad_next/commands/tests/test_download.py
datalad_next/commands/tests/test_ls_file_collection.py
datalad_next/commands/tests/test_results.py
datalad_next/commands/tests/test_status.py
datalad_next/commands/tests/test_tree.py
datalad_next/config/__init__.py
datalad_next/config/utils.py
datalad_next/config/tests/__init__.py
datalad_next/config/tests/test_core.py
datalad_next/config/tests/test_utils.py
datalad_next/constraints/__init__.py
datalad_next/constraints/base.py
datalad_next/constraints/basic.py
datalad_next/constraints/compound.py
datalad_next/constraints/dataset.py
datalad_next/constraints/exceptions.py
datalad_next/constraints/formats.py
datalad_next/constraints/git.py
datalad_next-1.5.0.dist-info/LICENSE
datalad_next-1.5.0.dist-info/METADATA
datalad_next-1.5.0.dist-info/WHEEL
datalad_next-1.5.0.dist-info/entry_points.txt
datalad_next-1.5.0.dist-info/top_level.txt
datalad_next-1.5.0.dist-info/RECORD
