Metadata-Version: 2.1
Name: datalad-next
Version: 1.5.0
Summary: What is next in DataLad
Home-page: https://github.com/datalad/datalad-next
Author: The DataLad Team and Contributors
Author-email: team@datalad.org
License: MIT
Classifier: Programming Language :: Python
Classifier: License :: OSI Approved :: BSD License
Classifier: Programming Language :: Python :: 3
Requires-Python: >=3.8
License-File: LICENSE
Requires-Dist: annexremote
Requires-Dist: datalad (>=0.18.4)
Requires-Dist: humanize
Requires-Dist: more-itertools
Provides-Extra: devel
Requires-Dist: pytest ; extra == 'devel'
Requires-Dist: pytest-cov ; extra == 'devel'
Requires-Dist: coverage ; extra == 'devel'
Requires-Dist: psutil ; extra == 'devel'
Requires-Dist: cheroot ; extra == 'devel'
Requires-Dist: wsgidav ; extra == 'devel'
Requires-Dist: webdavclient3 ; extra == 'devel'
Provides-Extra: httpsupport
Requires-Dist: requests ; extra == 'httpsupport'
Requires-Dist: requests-toolbelt ; extra == 'httpsupport'
